gwbackupy/__init__.py
gwbackupy/__main__.py
gwbackupy/global_properties.py
gwbackupy/gmail.py
gwbackupy/gwbackupy_cli.py
gwbackupy/helpers.py
gwbackupy/process_helpers.py
gwbackupy/filters/filter_interface.py
gwbackupy/filters/gmail_filter.py
gwbackupy/providers/gapi_gmail_service_wrapper.py
gwbackupy/providers/gapi_service_provider.py
gwbackupy/providers/gmail_service_provider.py
gwbackupy/providers/gmail_service_wrapper_interface.py
gwbackupy/providers/service_provider_interface.py
gwbackupy/storage/file_storage.py
gwbackupy/storage/storage_interface.py
gwbackupy-0.11.0.data/scripts/gwbackupy
gwbackupy-0.11.0.dist-info/LICENSE
gwbackupy-0.11.0.dist-info/METADATA
gwbackupy-0.11.0.dist-info/WHEEL
gwbackupy-0.11.0.dist-info/top_level.txt
gwbackupy-0.11.0.dist-info/RECORD
