Metadata-Version: 2.1
Name: gwbackupy
Version: 0.11.0
Summary: Open source Google Workspace backup solution.
Home-page: https://github.com/smartondev/gwbackupy
Author: Márton Somogyi
Author-email: info@smarton.dev
License: BSD 3-Clause "New" or "Revised" License
Classifier: Programming Language :: Python :: 3
Classifier: Programming Language :: Python :: 3.7
Classifier: Programming Language :: Python :: 3.8
Classifier: Programming Language :: Python :: 3.9
Classifier: Programming Language :: Python :: 3.10
Classifier: Programming Language :: Python :: 3.11
Classifier: License :: OSI Approved :: BSD License
Classifier: Operating System :: OS Independent
Classifier: Programming Language :: Python :: Implementation :: PyPy
Classifier: Operating System :: Microsoft :: Windows
Classifier: Operating System :: Unix
Classifier: Environment :: Console
Classifier: Programming Language :: Python
Classifier: Topic :: System :: Archiving :: Backup
Classifier: Topic :: Utilities
Classifier: Typing :: Typed
Requires-Python: >=3.7
License-File: LICENSE
Requires-Dist: google-api-python-client (~=2.71)
Requires-Dist: oauth2client (~=4.1)
Requires-Dist: pyopenssl (~=23.0)
Requires-Dist: tzlocal (~=4.2)
Requires-Dist: pytz (~=2022.7)
Requires-Dist: google-auth-httplib2 (~=0.1.0)
Requires-Dist: google-auth-oauthlib (~=0.8.0)
